napari_annotatorj/__init__.py
napari_annotatorj/_dock_widget _orig.py
napari_annotatorj/_dock_widget.py
napari_annotatorj/_function.py
napari_annotatorj/_reader.py
napari_annotatorj/_reader_orig.py
napari_annotatorj/_version.py
napari_annotatorj/_writer.py
napari_annotatorj/build_napari_annotatorj.bat
napari_annotatorj/load_image.py
napari_annotatorj/load_imagej_roi.py
napari_annotatorj/napari.yaml
napari_annotatorj/predict_unet.py
napari_annotatorj/startup_annotatorj.py
napari_annotatorj/_tests/__init__.py
napari_annotatorj/_tests/mimic_roiloading_frommask.py
napari_annotatorj/_tests/mimic_roiloading_fromtext.py
napari_annotatorj/_tests/test_annotatorj_fcns.py
napari_annotatorj/_tests/test_dock_widget.py
napari_annotatorj/_tests/test_function.py
napari_annotatorj/_tests/test_reader.py
napari_annotatorj/_tests/test_writer.py
napari_annotatorj/hooks/hook-OpenGL.py
napari_annotatorj/hooks/hook-freetype.py
napari_annotatorj/hooks/hook-ipykernel.py
napari_annotatorj/hooks/hook-napari.py
napari_annotatorj/hooks/hook-parso.py
napari_annotatorj/hooks/hook-vispy.py
napari_annotatorj/icon/annotatorj_logo_dark.svg
napari_annotatorj/icon/annotatorj_logo_light.svg
napari_annotatorj/icon/annotatorj_logo_red.svg
napari_annotatorj/icon/gear_icon_white.svg
napari_annotatorj/unet/LICENSE
napari_annotatorj/unet/README.md
napari_annotatorj/unet/data.py
napari_annotatorj/unet/main.py
napari_annotatorj/unet/model.py
napari_annotatorj/unet/zhixuhao_unet_repository.txt
napari_annotatorj-0.0.8.dist-info/LICENSE
napari_annotatorj-0.0.8.dist-info/METADATA
napari_annotatorj-0.0.8.dist-info/WHEEL
napari_annotatorj-0.0.8.dist-info/entry_points.txt
napari_annotatorj-0.0.8.dist-info/top_level.txt
napari_annotatorj-0.0.8.dist-info/RECORD
