Metadata-Version: 2.1
Name: napari-annotatorj
Version: 0.0.8
Summary: The napari adaptation of the ImageJ/Fiji plugin AnnotatorJ for easy image annotation.
Home-page: https://github.com/spreka/napari-annotatorj
Author: Reka Hollandi
Author-email: reka.hollandi@gmail.com
License: BSD-3-Clause
Project-URL: Bug Tracker, https://github.com/spreka/napari-annotatorj/issues
Project-URL: Documentation, https://github.com/spreka/napari-annotatorj#README.md
Project-URL: Source Code, https://github.com/spreka/napari-annotatorj
Project-URL: User Support, https://github.com/spreka/napari-annotatorj/issues
Classifier: Development Status :: 3 - Alpha
Classifier: Intended Audience :: Developers
Classifier: Framework :: napari
Classifier: Topic :: Software Development :: Testing
Classifier: Programming Language :: Python
Classifier: Programming Language :: Python :: 3
Classifier: Programming Language :: Python :: 3.8
Classifier: Programming Language :: Python :: 3.9
Classifier: Programming Language :: Python :: 3.10
Classifier: Operating System :: OS Independent
Classifier: License :: OSI Approved :: BSD License
Requires-Python: >=3.7
License-File: LICENSE
Requires-Dist: napari
Requires-Dist: napari-plugin-engine >=0.1.4
Requires-Dist: numpy
Requires-Dist: roifile
Requires-Dist: scikit-image
Requires-Dist: opencv-python >=4.5.5
Requires-Dist: keras
Requires-Dist: tensorflow >=2.5.0
Requires-Dist: tifffile
Requires-Dist: imagecodecs
Requires-Dist: tqdm
Requires-Dist: pyqtgraph
